{
  "version": "8.2.1",
  "category": "HUMAN",
  "subcategories": [
    {
      "subcategory": "BLOW",
      "category_id": "HMNBlow",
      "category_short": "HMN",
      "explanation": [
        "Blowing air",
        "blowing up a balloon",
        "blowing out candles",
        "etc. See also HUMAN-BREATH for less forceful breathing."
      ],
      "synonyms": [
        "Adult",
        "Blow",
        "Child",
        "Female",
        "Male",
        "Man",
        "Person",
        "Woman"
      ]
    },
    {
      "subcategory": "BREATH",
      "category_id": "HMNBrth",
      "category_short": "HMN",
      "explanation": [
        "Breathing",
        "normal to heavy",
        "big inhales",
        "sighs."
      ],
      "synonyms": [
        "Adult",
        "Asphyxiate",
        "Asthma",
        "Breath",
        "Breathing",
        "Breaths",
        "Child",
        "Exhalation",
        "Exhale",
        "Exhaled",
        "Exhales",
        "Exhaling",
        "Female",
        "Gasp",
        "Gasping",
        "Heave",
        "Huff",
        "Huffing",
        "Hyperventilate",
        "Hyperventilating",
        "Inhalation",
        "Inhale",
        "Inhaled",
        "Inhales",
        "Inhaling",
        "Labored",
        "Male",
        "Man",
        "Meditation",
        "Pant",
        "Panting",
        "Person",
        "Puffing",
        "Respiration",
        "Sigh",
        "Suffocate",
        "Suffocates",
        "Suffocating",
        "Wheeze",
        "Wheezing",
        "Whoop",
        "Woman"
      ]
    },
    {
      "subcategory": "BURP",
      "category_id": "HMNBurp",
      "category_short": "HMN",
      "explanation": [
        "Human belches",
        "burps."
      ],
      "synonyms": [
        "Adult",
        "Belch",
        "Belching",
        "Burp",
        "Burping",
        "Child",
        "Female",
        "Hiccup",
        "Male",
        "Man",
        "Person",
        "Woman"
      ]
    },
    {
      "subcategory": "COUGH",
      "category_id": "HMNCough",
      "category_short": "HMN",
      "explanation": [
        "Human coughs and coughing."
      ],
      "synonyms": [
        "Adult",
        "Ahem",
        "Bronchitis",
        "Child",
        "Choking",
        "Clear",
        "Clearing",
        "Convulse",
        "Coughing",
        "Covid",
        "Expectoration",
        "Female",
        "Gag",
        "Hack",
        "Hacking",
        "Hiccough",
        "Hiccoughing",
        "Hiccoughs",
        "Hoarse",
        "Male",
        "Man",
        "Person",
        "Throat",
        "Wet",
        "Whooping",
        "Woman"
      ]
    },
    {
      "subcategory": "HEARTBEAT",
      "category_id": "HMNHart",
      "category_short": "HMN",
      "explanation": [
        "Heartbeats",
        "both literal as in a Dr. office",
        "and stylized or designed heartbeats."
      ],
      "synonyms": [
        "Adult",
        "Arrhythmia",
        "Arrhythmic",
        "Arrythmia",
        "Beating",
        "Cardiac",
        "Child",
        "Coronary",
        "EKG",
        "Female",
        "Fetal",
        "Fibrillation",
        "Heart",
        "Male",
        "Man",
        "Palpitate",
        "Palpitates",
        "Palpitating",
        "Palpitation",
        "Palpitations",
        "Person",
        "Pulsate",
        "Pulsated",
        "Pulsates",
        "Pulsating",
        "Pulse",
        "Rate",
        "Rhythm",
        "Woman"
      ]
    },
    {
      "subcategory": "KISS",
      "category_id": "HMNKiss",
      "category_short": "HMN",
      "explanation": [
        "Human kissing."
      ],
      "synonyms": [
        "Adult",
        "Child",
        "Female",
        "French",
        "Hickey",
        "Kiss",
        "Lips",
        "Make",
        "Male",
        "Man",
        "Necking",
        "Out",
        "Peck",
        "Person",
        "Smooch",
        "Smooching",
        "Snog",
        "Woman"
      ]
    },
    {
      "subcategory": "MISC",
      "category_id": "HMNMisc",
      "category_short": "HMN",
      "explanation": [
        "Human sounds not fitting another category in this list."
      ],
      "synonyms": [
        "Adult",
        "Child",
        "Female",
        "Male",
        "Man",
        "Miscellaneous",
        "Person",
        "Woman"
      ]
    },
    {
      "subcategory": "PEE",
      "category_id": "HMNPee",
      "category_short": "HMN",
      "explanation": [
        "Human urinating."
      ],
      "synonyms": [
        "Adult",
        "Child",
        "Female",
        "Male",
        "Man",
        "Micturition",
        "Peeing",
        "Person",
        "Piss",
        "Tinkle",
        "Urinate",
        "Urinating",
        "Urination",
        "Wee",
        "Wizz",
        "Woman"
      ]
    },
    {
      "subcategory": "SKIN",
      "category_id": "HMNSkin",
      "category_short": "HMN",
      "explanation": [
        "Human skin",
        "Scratching",
        "handshakes",
        "skin on skin action",
        "back rubbing",
        "etc."
      ],
      "synonyms": [
        "Adult",
        "Backrub",
        "Brush",
        "Caress",
        "Child",
        "Clap",
        "Dermis",
        "Female",
        "Flick",
        "Grab",
        "Hand",
        "Handshake",
        "Itch",
        "Male",
        "Man",
        "Massage",
        "Pat",
        "Person",
        "Pores",
        "Rash",
        "Rub",
        "Rubbing",
        "Scratch",
        "Scratching",
        "Skin",
        "Slap",
        "Tap",
        "Woman"
      ]
    },
    {
      "subcategory": "SNEEZE",
      "category_id": "HMNSneez",
      "category_short": "HMN",
      "explanation": [
        "Human sneezing."
      ],
      "synonyms": [
        "Achoo",
        "Adult",
        "Ah-Choo",
        "Ahchoo",
        "Allergic",
        "Allergy",
        "Child",
        "Female",
        "Fever",
        "Hay",
        "Male",
        "Man",
        "Nasal",
        "Person",
        "Sinus",
        "Sneeze",
        "Woman"
      ]
    },
    {
      "subcategory": "SNIFF",
      "category_id": "HMNSniff",
      "category_short": "HMN",
      "explanation": [
        "Human sniffing",
        "smelling."
      ],
      "synonyms": [
        "Adult",
        "Child",
        "Female",
        "Inhalation",
        "Inhale",
        "Male",
        "Man",
        "Nose",
        "Odor",
        "Person",
        "Smell",
        "Sniff",
        "Sniffing",
        "Sniffle",
        "Snivel",
        "Snort",
        "Snorting",
        "Snuffle",
        "Whiff",
        "Woman"
      ]
    },
    {
      "subcategory": "SNORE",
      "category_id": "HMNSnor",
      "category_short": "HMN",
      "explanation": [
        "Human snoring."
      ],
      "synonyms": [
        "Adult",
        "Apnea",
        "Breathing",
        "Child",
        "Congested",
        "Doze",
        "Dozing",
        "Female",
        "Heavy",
        "Male",
        "Man",
        "Person",
        "Slumber",
        "Snooze",
        "Snore",
        "Snoring",
        "Woman",
        "ZZZ"
      ]
    },
    {
      "subcategory": "SPIT",
      "category_id": "HMNSpit",
      "category_short": "HMN",
      "explanation": [
        "Human spits."
      ],
      "synonyms": [
        "Adult",
        "Child",
        "Drool",
        "Expectoration",
        "Female",
        "Gob",
        "Hawk",
        "Hock",
        "Male",
        "Man",
        "Mucus",
        "Person",
        "Phlegm",
        "Saliva",
        "Slobber",
        "Spew",
        "Spit",
        "Spitoon",
        "Spitting",
        "Spittle",
        "Spittoon",
        "Sputum",
        "Woman"
      ]
    },
    {
      "subcategory": "VOMIT",
      "category_id": "HMNVomit",
      "category_short": "HMN",
      "explanation": [
        "Human vomiting."
      ],
      "synonyms": [
        "Adult",
        "Barf",
        "Barfing",
        "Child",
        "Chunder",
        "Expunge",
        "Female",
        "Gag",
        "Gagging",
        "Heave",
        "Hurl",
        "Male",
        "Man",
        "Nausea",
        "Nauseous",
        "Person",
        "Puke",
        "Pukes",
        "Reflex",
        "Reflux",
        "Regurgitate",
        "Regurgitated",
        "Regurgitation",
        "Retch",
        "Retched",
        "Retching",
        "Seasick",
        "Spew",
        "Throwing",
        "Up",
        "Upchuck",
        "Vomit",
        "Vomitus",
        "Woman"
      ]
    }
  ]
}
