{
 "version": "8.2.1",
 "category": "TRAINS",
 "subcategories": [
  {
   "subcategory": "BRAKE",
   "category_id": "TRNBrake",
   "category_short": "TRN",
   "explanation": [
    "Screeching metalic train brake wheels",
    "subway brakes. Usually a piercing sound."
   ],
   "synonyms": [
    "Bake",
    "Brake",
    "Brakes",
    "Braking",
    "Breaks",
    "Grind",
    "Halting",
    "Pads",
    "Rail",
    "Railcar",
    "Railway",
    "Rolling",
    "Screech",
    "Shoes",
    "Stock"
   ],
   "acoustic_signature": {
    "morphology": "friction",
    "separability": "signal_narrowable",
    "gates": [
     {
      "feature": "length_seconds",
      "min": 0.3,
      "max": 120.0
     }
    ],
    "priors": [
     {
      "feature": "spectral_centroid_hz",
      "mean": 3800.0,
      "deviation": 1900.0,
      "transform": "log",
      "weight": 0.9,
      "provenance": {
       "source": "reasoned"
      }
     },
     {
      "feature": "high_band_energy",
      "mean": 0.55,
      "deviation": 0.18,
      "transform": "linear",
      "weight": 0.8,
      "provenance": {
       "source": "reasoned"
      }
     },
     {
      "feature": "low_band_energy",
      "mean": 0.1,
      "deviation": 0.09,
      "transform": "linear",
      "weight": 0.7,
      "provenance": {
       "source": "reasoned"
      }
     },
     {
      "feature": "harmonicity",
      "mean": 0.45,
      "deviation": 0.22,
      "transform": "linear",
      "weight": 0.7,
      "provenance": {
       "source": "reasoned"
      }
     },
     {
      "feature": "inharmonicity",
      "mean": 0.55,
      "deviation": 0.22,
      "transform": "linear",
      "weight": 0.7,
      "provenance": {
       "source": "reasoned"
      }
     },
     {
      "feature": "pitch_hz",
      "mean": 1600.0,
      "deviation": 900.0,
      "transform": "log",
      "weight": 0.6,
      "provenance": {
       "source": "reasoned"
      }
     },
     {
      "feature": "spectral_centroid_deviation_hz",
      "mean": 900.0,
      "deviation": 500.0,
      "transform": "linear",
      "weight": 0.7,
      "provenance": {
       "source": "reasoned"
      }
     },
     {
      "feature": "spectral_flux",
      "mean": 0.2,
      "deviation": 0.09,
      "transform": "linear",
      "weight": 0.6,
      "provenance": {
       "source": "reasoned"
      }
     },
     {
      "feature": "root_mean_square_level",
      "mean": 0.24,
      "deviation": 0.12,
      "transform": "linear",
      "weight": 0.5,
      "provenance": {
       "source": "reasoned"
      }
     },
     {
      "feature": "stationarity",
      "mean": 0.45,
      "deviation": 0.2,
      "transform": "linear",
      "weight": 0.6,
      "provenance": {
       "source": "reasoned"
      }
     },
     {
      "feature": "sustain_ratio",
      "mean": 0.45,
      "deviation": 0.2,
      "transform": "linear",
      "weight": 0.4,
      "provenance": {
       "source": "reasoned"
      }
     },
     {
      "feature": "length_seconds",
      "mean": 6.0,
      "deviation": 5.0,
      "transform": "log",
      "weight": 0.4,
      "provenance": {
       "source": "reasoned"
      }
     },
     {
      "feature": "zero_crossings_per_second",
      "mean": 5500.0,
      "deviation": 3000.0,
      "transform": "log",
      "weight": 0.5,
      "provenance": {
       "source": "reasoned"
      }
     }
    ],
    "discriminators": [
     "UCS says it outright: 'Usually a piercing sound.' A brake squeal is a STICK-SLIP friction oscillation — an unstable, WANDERING, INHARMONIC high tone. So it is by far the brightest thing in TRAINS (spectral_centroid_hz ~3.8 kHz, high_band_energy ~0.55) while carrying enough harmonicity to actually squeal, with high inharmonicity and a large spectral_centroid_deviation_hz because the pitch will not sit still.",
     "Against every rolling and engine subcategory (TRAINS-DIESEL, TRAINS-ELECTRIC, TRAINS-CLACK): the spectral tilt is INVERTED. Those are LF-dominant; this is HF-dominant. That is a real separation.",
     "Against TRAINS-HORN: both are loud and pitched, but a horn is STABLE, HARMONIC and LOW (~300 Hz), while a squeal is unstable, inharmonic and in the kilohertz. No overlap.",
     "Narrowable, not separable, because metal-on-metal screech is acoustically the same wherever it comes from — METAL-FRICTION or VEHICLES-BRAKE will look identical."
    ],
    "confusable_with": [
     "TRNMech",
     "TRNClak",
     "TRNSbwy",
     "TRNHorn",
     "TRNElec"
    ]
   }
  },
  {
   "subcategory": "CLACK",
   "category_id": "TRNClak",
   "category_short": "TRN",
   "explanation": [
    "Train clacks isolated",
    "constant clacking of trains passing or running."
   ],
   "synonyms": [
    "Clack",
    "Clattering",
    "Clickety-Clack",
    "Railway",
    "Rattling",
    "Rhythmic",
    "Track",
    "Train",
    "Wheel"
   ],
   "acoustic_signature": {
    "morphology": "rhythmic",
    "separability": "signal_separable",
    "gates": [
     {
      "feature": "length_seconds",
      "min": 1.0,
      "max": 600.0
     },
     {
      "feature": "onset_periodicity",
      "min": 0.35
     },
     {
      "feature": "transient_count",
      "min": 4.0
     }
    ],
    "priors": [
     {
      "feature": "onset_periodicity",
      "mean": 0.8,
      "deviation": 0.13,
      "transform": "linear",
      "weight": 1.0,
      "provenance": {
       "source": "reasoned"
      }
     },
     {
      "feature": "onset_rate_per_second",
      "mean": 4.5,
      "deviation": 3.0,
      "transform": "log",
      "weight": 0.9,
      "provenance": {
       "source": "reasoned"
      }
     },
     {
      "feature": "transient_count",
      "mean": 60.0,
      "deviation": 50.0,
      "transform": "log",
      "weight": 0.6,
      "provenance": {
       "source": "reasoned"
      }
     },
     {
      "feature": "crest_factor",
      "mean": 7.0,
      "deviation": 2.5,
      "transform": "log",
      "weight": 0.8,
      "provenance": {
       "source": "reasoned"
      }
     },
     {
      "feature": "envelope_attack_seconds",
      "mean": 0.004,
      "deviation": 2.718,
      "transform": "log",
      "weight": 0.7,
      "provenance": {
       "source": "reasoned"
      }
     },
     {
      "feature": "mid_band_energy",
      "mean": 0.42,
      "deviation": 0.16,
      "transform": "linear",
      "weight": 0.5,
      "provenance": {
       "source": "reasoned"
      }
     },
     {
      "feature": "low_band_energy",
      "mean": 0.32,
      "deviation": 0.15,
      "transform": "linear",
      "weight": 0.5,
      "provenance": {
       "source": "reasoned"
      }
     },
     {
      "feature": "high_band_energy",
      "mean": 0.26,
      "deviation": 0.14,
      "transform": "linear",
      "weight": 0.4,
      "provenance": {
       "source": "reasoned"
      }
     },
     {
      "feature": "inharmonicity",
      "mean": 0.6,
      "deviation": 0.22,
      "transform": "linear",
      "weight": 0.4,
      "provenance": {
       "source": "reasoned"
      }
     },
     {
      "feature": "harmonicity",
      "mean": 0.18,
      "deviation": 0.13,
      "transform": "linear",
      "weight": 0.5,
      "provenance": {
       "source": "reasoned"
      }
     },
     {
      "feature": "beats_per_minute",
      "mean": 270.0,
      "deviation": 160.0,
      "transform": "log",
      "weight": 0.4,
      "provenance": {
       "source": "reasoned"
      }
     },
     {
      "feature": "spectral_flux",
      "mean": 0.22,
      "deviation": 0.09,
      "transform": "linear",
      "weight": 0.5,
      "provenance": {
       "source": "reasoned"
      }
     },
     {
      "feature": "length_seconds",
      "mean": 25.0,
      "deviation": 25.0,
      "transform": "log",
      "weight": 0.3,
      "provenance": {
       "source": "reasoned"
      }
     },
     {
      "feature": "decay_time_seconds_60db",
      "mean": 0.08,
      "deviation": 2.399,
      "transform": "log",
      "weight": 0.5,
      "provenance": {
       "source": "reasoned"
      }
     }
    ],
    "discriminators": [
     "The textbook rhythmic detector, and one of the few places where a rhythm detector alone is nearly sufficient. Wheels crossing rail joints produce a PERIODIC IMPULSE TRAIN whose rate is set by bogie spacing and train speed — a few clacks per second, each a sharp metallic transient with a short decay. onset_periodicity is very high (~0.80, gated >= 0.35), onset_rate_per_second sits in the 3-8/s band, crest_factor is high (~7) because the signal is mostly gaps, and envelope_attack_seconds is a few milliseconds.",
     "Nothing else in TRAINS is BOTH impulsive AND strictly periodic at that rate.",
     "Against TRAINS-STEAM: chuffs are also periodic but SLOWER (~1-3/s), softer-attacked, and ride on a continuous HF hiss bed that clacking lacks.",
     "Against TRAINS-MECHANISM: coupling clanks are ISOLATED impacts, not a sustained periodic train — hence the transient_count >= 4 gate here, which a couple of shunting bangs will not pass.",
     "A decelerating train sweeps the clack rate downward; the periodicity survives the sweep, the rate does not, so the rate prior is given a wide deviation."
    ],
    "confusable_with": [
     "TRNSteam",
     "TRNMech",
     "TRNSbwy",
     "TRNElec",
     "TRNDiesl"
    ]
   }
  },
  {
   "subcategory": "DOOR",
   "category_id": "TRNDoor",
   "category_short": "TRN",
   "explanation": [
    "Train doors",
    "sliding doors in passenger or freight trains. Some overlap with general DOORS category and possibly VEHICLES-DOOR."
   ],
   "synonyms": [
    "Access",
    "Boxcar",
    "Cab",
    "Caboose",
    "Car",
    "Coach",
    "Door",
    "Hatch",
    "Rail",
    "Railway",
    "Subway",
    "Train"
   ],
   "acoustic_signature": {
    "morphology": "impulsive_with_tail",
    "separability": "semantic_only",
    "gates": [
     {
      "feature": "length_seconds",
      "min": 0.05,
      "max": 30.0
     }
    ],
    "priors": [
     {
      "feature": "envelope_attack_seconds",
      "mean": 0.01,
      "deviation": 2.718,
      "transform": "log",
      "weight": 0.5,
      "provenance": {
       "source": "reasoned"
      }
     },
     {
      "feature": "crest_factor",
      "mean": 7.5,
      "deviation": 3.2,
      "transform": "log",
      "weight": 0.5,
      "provenance": {
       "source": "reasoned"
      }
     },
     {
      "feature": "envelope_temporal_centroid",
      "mean": 0.35,
      "deviation": 0.15,
      "transform": "linear",
      "weight": 0.4,
      "provenance": {
       "source": "reasoned"
      }
     },
     {
      "feature": "length_seconds",
      "mean": 2.5,
      "deviation": 2.0,
      "transform": "log",
      "weight": 0.5,
      "provenance": {
       "source": "reasoned"
      }
     },
     {
      "feature": "transient_count",
      "mean": 3.0,
      "deviation": 3.0,
      "transform": "log",
      "weight": 0.4,
      "provenance": {
       "source": "reasoned"
      }
     },
     {
      "feature": "high_band_energy",
      "mean": 0.3,
      "deviation": 0.16,
      "transform": "linear",
      "weight": 0.3,
      "provenance": {
       "source": "reasoned"
      }
     },
     {
      "feature": "decay_time_seconds_60db",
      "mean": 0.3,
      "deviation": 2.301,
      "transform": "log",
      "weight": 0.4,
      "provenance": {
       "source": "reasoned"
      }
     },
     {
      "feature": "stationarity",
      "mean": 0.35,
      "deviation": 0.18,
      "transform": "linear",
      "weight": 0.4,
      "provenance": {
       "source": "reasoned"
      }
     }
    ],
    "discriminators": [
     "A sliding subway door is a pneumatic hiss plus a hard end-stop clunk — but so is a bus door, and UCS itself flags the overlap with the general DOORS category and VEHICLES-DOOR. Semantic.",
     "The gates still earn their keep: an event of seconds, not a rolling bed, which prunes it against TRAINS-INTERIOR, TRAINS-SUBWAY and the locomotive subcategories."
    ],
    "confusable_with": [
     "AERODoor",
     "BOATDoor",
     "TRNMech",
     "TRNSbwy"
    ]
   }
  },
  {
   "subcategory": "DIESEL",
   "category_id": "TRNDiesl",
   "category_short": "TRN",
   "explanation": [
    "Freight trains",
    "large commercial diesel locomotives."
   ],
   "synonyms": [
    "Diesel",
    "Diesel-Electric",
    "Diesel-Powered",
    "Freight",
    "Locomotive",
    "Passenger",
    "Powerhouse",
    "Railcar",
    "Railway",
    "Train"
   ],
   "acoustic_signature": {
    "morphology": "rhythmic",
    "separability": "signal_narrowable",
    "gates": [
     {
      "feature": "length_seconds",
      "min": 1.0,
      "max": 900.0
     }
    ],
    "priors": [
     {
      "feature": "onset_periodicity",
      "mean": 0.58,
      "deviation": 0.2,
      "transform": "linear",
      "weight": 0.8,
      "provenance": {
       "source": "reasoned"
      }
     },
     {
      "feature": "onset_rate_per_second",
      "mean": 30.0,
      "deviation": 22.0,
      "transform": "log",
      "weight": 0.6,
      "provenance": {
       "source": "reasoned"
      }
     },
     {
      "feature": "low_band_energy",
      "mean": 0.6,
      "deviation": 0.15,
      "transform": "linear",
      "weight": 0.9,
      "provenance": {
       "source": "reasoned"
      }
     },
     {
      "feature": "spectral_centroid_hz",
      "mean": 450.0,
      "deviation": 300.0,
      "transform": "log",
      "weight": 0.7,
      "provenance": {
       "source": "reasoned"
      }
     },
     {
      "feature": "total_harmonic_distortion",
      "mean": 0.35,
      "deviation": 0.2,
      "transform": "linear",
      "weight": 0.6,
      "provenance": {
       "source": "reasoned"
      }
     },
     {
      "feature": "harmonicity",
      "mean": 0.3,
      "deviation": 0.17,
      "transform": "linear",
      "weight": 0.6,
      "provenance": {
       "source": "reasoned"
      }
     },
     {
      "feature": "spectral_flatness",
      "mean": 0.42,
      "deviation": 0.17,
      "transform": "linear",
      "weight": 0.5,
      "provenance": {
       "source": "reasoned"
      }
     },
     {
      "feature": "root_mean_square_level",
      "mean": 0.26,
      "deviation": 0.12,
      "transform": "linear",
      "weight": 0.5,
      "provenance": {
       "source": "reasoned"
      }
     },
     {
      "feature": "lufs",
      "mean": -14.0,
      "deviation": 6.0,
      "transform": "linear",
      "weight": 0.4,
      "provenance": {
       "source": "reasoned"
      }
     },
     {
      "feature": "stationarity",
      "mean": 0.68,
      "deviation": 0.18,
      "transform": "linear",
      "weight": 0.5,
      "provenance": {
       "source": "reasoned"
      }
     },
     {
      "feature": "spectral_slope_db_per_octave",
      "mean": -10.0,
      "deviation": 4.0,
      "transform": "linear",
      "weight": 0.5,
      "provenance": {
       "source": "reasoned"
      }
     },
     {
      "feature": "length_seconds",
      "mean": 40.0,
      "deviation": 40.0,
      "transform": "log",
      "weight": 0.3,
      "provenance": {
       "source": "reasoned"
      }
     },
     {
      "feature": "crest_factor",
      "mean": 4.0,
      "deviation": 1.5,
      "transform": "log",
      "weight": 0.4,
      "provenance": {
       "source": "reasoned"
      }
     }
    ],
    "discriminators": [
     "A big diesel prime mover: LOW, LOUD, DISTORTED, with an exhaust firing pulse train. low_band_energy ~0.60, heavy total_harmonic_distortion, moderate-to-high onset_periodicity at tens of pulses per second.",
     "Against TRAINS-ELECTRIC: this is the one intra-TRAINS engine boundary the signal can actually see, and it is worth stating precisely. A traction motor is a clean tonal WHINE — high harmonicity, low spectral_flatness, a centroid an octave or more higher, near-zero combustion periodicity, and a pitch that GLIDES with speed. A diesel is noisy, LF, distorted and pulse-periodic. Genuinely narrowable.",
     "Against TRAINS-CLACK: a clack is a sparse impulsive train (a few per second, crest_factor ~7); the diesel is a continuous bed (crest_factor ~4). Both often appear in one recording — prefer whichever dominates the energy.",
     "Freight versus passenger diesel is semantic."
    ],
    "confusable_with": [
     "TRNElec",
     "TRNSbwy",
     "TRNClak",
     "TRNMisc",
     "TRNSteam"
    ]
   }
  },
  {
   "subcategory": "ELECTRIC",
   "category_id": "TRNElec",
   "category_short": "TRN",
   "explanation": [
    "Commuter trains",
    "elevated trains",
    "light rail",
    "SUBWAYS have their own category."
   ],
   "synonyms": [
    "City",
    "Commuter",
    "Inter-City",
    "Light",
    "Line",
    "Maglev",
    "Monorail",
    "Rail",
    "Railway",
    "Regional",
    "Train"
   ],
   "acoustic_signature": {
    "morphology": "sustained_tonal",
    "separability": "signal_narrowable",
    "gates": [
     {
      "feature": "length_seconds",
      "min": 1.0,
      "max": 900.0
     }
    ],
    "priors": [
     {
      "feature": "harmonicity",
      "mean": 0.52,
      "deviation": 0.19,
      "transform": "linear",
      "weight": 0.9,
      "provenance": {
       "source": "reasoned"
      }
     },
     {
      "feature": "spectral_flatness",
      "mean": 0.28,
      "deviation": 0.14,
      "transform": "linear",
      "weight": 0.9,
      "provenance": {
       "source": "reasoned"
      }
     },
     {
      "feature": "pitch_hz",
      "mean": 480.0,
      "deviation": 320.0,
      "transform": "log",
      "weight": 0.7,
      "provenance": {
       "source": "reasoned"
      }
     },
     {
      "feature": "pitch_slope_semitones_per_second",
      "mean": 1.2,
      "deviation": 3.5,
      "transform": "linear",
      "weight": 0.7,
      "provenance": {
       "source": "reasoned"
      }
     },
     {
      "feature": "onset_periodicity",
      "mean": 0.2,
      "deviation": 0.16,
      "transform": "linear",
      "weight": 0.8,
      "provenance": {
       "source": "reasoned"
      }
     },
     {
      "feature": "total_harmonic_distortion",
      "mean": 0.1,
      "deviation": 0.09,
      "transform": "linear",
      "weight": 0.6,
      "provenance": {
       "source": "reasoned"
      }
     },
     {
      "feature": "spectral_centroid_hz",
      "mean": 1300.0,
      "deviation": 800.0,
      "transform": "log",
      "weight": 0.6,
      "provenance": {
       "source": "reasoned"
      }
     },
     {
      "feature": "mid_band_energy",
      "mean": 0.45,
      "deviation": 0.17,
      "transform": "linear",
      "weight": 0.5,
      "provenance": {
       "source": "reasoned"
      }
     },
     {
      "feature": "low_band_energy",
      "mean": 0.3,
      "deviation": 0.15,
      "transform": "linear",
      "weight": 0.5,
      "provenance": {
       "source": "reasoned"
      }
     },
     {
      "feature": "partial_count",
      "mean": 6.0,
      "deviation": 4.0,
      "transform": "log",
      "weight": 0.4,
      "provenance": {
       "source": "reasoned"
      }
     },
     {
      "feature": "stationarity",
      "mean": 0.7,
      "deviation": 0.17,
      "transform": "linear",
      "weight": 0.5,
      "provenance": {
       "source": "reasoned"
      }
     },
     {
      "feature": "length_seconds",
      "mean": 35.0,
      "deviation": 35.0,
      "transform": "log",
      "weight": 0.3,
      "provenance": {
       "source": "reasoned"
      }
     }
    ],
    "discriminators": [
     "A traction motor and its inverter make a TONE, not a rumble: harmonicity ~0.52, spectral_flatness down at ~0.28, and a measurable pitch_hz in the hundreds of hertz that GLIDES monotonically with train speed (pitch_slope_semitones_per_second nonzero) — the characteristic accelerating whine. And, decisively, no combustion pulse train: onset_periodicity ~0.20.",
     "That pairing — TONAL plus NON-PULSED — is precisely what TRAINS-DIESEL is not (noisy, LF, distorted, pulse-periodic). It is the real signal boundary inside this category.",
     "Against TRAINS-SUBWAY: acoustically the SAME electric traction. UCS separates them by location ('overtly underground sounding'), which surfaces as reverberation, not as a source feature — semantic, with only a weak tunnel-reverb tell.",
     "UCS routes cable-hauled trams to TRAINS-TRAM and electric trams here."
    ],
    "confusable_with": [
     "TRNDiesl",
     "TRNSbwy",
     "TRNHspd",
     "TRNTram",
     "TRNClak"
    ]
   }
  },
  {
   "subcategory": "HIGH SPEED",
   "category_id": "TRNHspd",
   "category_short": "TRN",
   "explanation": [
    "Hi-Tech trains",
    "Maglev",
    "monorails",
    "Hyperloops",
    "bullet trains."
   ],
   "synonyms": [
    "350",
    "AGV",
    "AVE",
    "Brightline",
    "Bullet",
    "CRH",
    "Eurostar",
    "Express",
    "Hi-Tech",
    "High-Speed",
    "Hyperloop",
    "ICE",
    "Maglev",
    "Monorails",
    "Railway",
    "Rapid",
    "Shinkansen",
    "Talgo",
    "TGV",
    "Train",
    "X2000"
   ],
   "acoustic_signature": {
    "morphology": "sustained_noise",
    "separability": "semantic_only",
    "gates": [
     {
      "feature": "length_seconds",
      "min": 0.5,
      "max": 600.0
     }
    ],
    "priors": [
     {
      "feature": "spectral_centroid_hz",
      "mean": 1800.0,
      "deviation": 1000.0,
      "transform": "log",
      "weight": 0.5,
      "provenance": {
       "source": "reasoned"
      }
     },
     {
      "feature": "high_band_energy",
      "mean": 0.35,
      "deviation": 0.17,
      "transform": "linear",
      "weight": 0.5,
      "provenance": {
       "source": "reasoned"
      }
     },
     {
      "feature": "spectral_flatness",
      "mean": 0.58,
      "deviation": 0.17,
      "transform": "linear",
      "weight": 0.5,
      "provenance": {
       "source": "reasoned"
      }
     },
     {
      "feature": "spectral_centroid_slope_hz_per_second",
      "mean": 0.0,
      "deviation": 500.0,
      "transform": "linear",
      "weight": 0.4,
      "provenance": {
       "source": "reasoned"
      }
     },
     {
      "feature": "onset_periodicity",
      "mean": 0.25,
      "deviation": 0.2,
      "transform": "linear",
      "weight": 0.4,
      "provenance": {
       "source": "reasoned"
      }
     },
     {
      "feature": "root_mean_square_level",
      "mean": 0.28,
      "deviation": 0.13,
      "transform": "linear",
      "weight": 0.4,
      "provenance": {
       "source": "reasoned"
      }
     },
     {
      "feature": "envelope_temporal_centroid",
      "mean": 0.48,
      "deviation": 0.12,
      "transform": "linear",
      "weight": 0.3,
      "provenance": {
       "source": "reasoned"
      }
     },
     {
      "feature": "stationarity",
      "mean": 0.55,
      "deviation": 0.2,
      "transform": "linear",
      "weight": 0.4,
      "provenance": {
       "source": "reasoned"
      }
     },
     {
      "feature": "length_seconds",
      "mean": 15.0,
      "deviation": 12.0,
      "transform": "log",
      "weight": 0.4,
      "provenance": {
       "source": "reasoned"
      }
     },
     {
      "feature": "harmonicity",
      "mean": 0.25,
      "deviation": 0.18,
      "transform": "linear",
      "weight": 0.3,
      "provenance": {
       "source": "reasoned"
      }
     }
    ],
    "discriminators": [
     "At speed, aerodynamic noise swamps everything: the wheel clack blurs away (onset_periodicity falls) and what is left is a brief, bright, broadband WHOOSH. There is a real physical reason the rhythmic signature is ABSENT here — high-speed lines use continuously welded rail, so the joints that make a clack do not exist.",
     "A high-speed pass-by carries a strong DOPPLER: spectral_centroid_slope_hz_per_second passes through zero with a rise-fall envelope. That is measurable, but it identifies a PASS-BY, not a bullet train.",
     "Which is why this is semantic_only: a TGV, a Shinkansen and a fast conventional express are the same aerodynamic roar. The synonyms (Shinkansen, TGV, Maglev, Hyperloop) carry it."
    ],
    "confusable_with": [
     "TRNElec",
     "TRNSbwy",
     "TRNMisc",
     "TRNDiesl"
    ]
   }
  },
  {
   "subcategory": "HORN",
   "category_id": "TRNHorn",
   "category_short": "TRN",
   "explanation": [
    "Train horns",
    "subway horns. A steam train whistle would likely go into WHISTLES-MECHANICAL."
   ],
   "synonyms": [
    "Air",
    "Commuter",
    "Electric",
    "Freight",
    "High-Speed",
    "Horn",
    "Light",
    "Locomotive",
    "Passenger",
    "Rail",
    "Railway",
    "Regional",
    "Subway",
    "Train",
    "Tram"
   ],
   "acoustic_signature": {
    "morphology": "sustained_tonal",
    "separability": "signal_separable",
    "gates": [
     {
      "feature": "length_seconds",
      "min": 0.2,
      "max": 60.0
     },
     {
      "feature": "harmonicity",
      "min": 0.35
     },
     {
      "feature": "pitch_hz",
      "min": 60.0,
      "max": 900.0
     }
    ],
    "priors": [
     {
      "feature": "pitch_hz",
      "mean": 300.0,
      "deviation": 170.0,
      "transform": "log",
      "weight": 1.0,
      "provenance": {
       "source": "reasoned"
      }
     },
     {
      "feature": "harmonicity",
      "mean": 0.7,
      "deviation": 0.15,
      "transform": "linear",
      "weight": 1.0,
      "provenance": {
       "source": "reasoned"
      }
     },
     {
      "feature": "spectral_flatness",
      "mean": 0.16,
      "deviation": 0.1,
      "transform": "linear",
      "weight": 0.9,
      "provenance": {
       "source": "reasoned"
      }
     },
     {
      "feature": "partial_count",
      "mean": 12.0,
      "deviation": 6.0,
      "transform": "log",
      "weight": 0.7,
      "provenance": {
       "source": "reasoned"
      }
     },
     {
      "feature": "inharmonicity",
      "mean": 0.22,
      "deviation": 0.15,
      "transform": "linear",
      "weight": 0.5,
      "provenance": {
       "source": "reasoned"
      }
     },
     {
      "feature": "pitch_slope_semitones_per_second",
      "mean": 0.0,
      "deviation": 2.0,
      "transform": "linear",
      "weight": 0.8,
      "provenance": {
       "source": "reasoned"
      }
     },
     {
      "feature": "sustain_ratio",
      "mean": 0.68,
      "deviation": 0.18,
      "transform": "linear",
      "weight": 0.8,
      "provenance": {
       "source": "reasoned"
      }
     },
     {
      "feature": "envelope_sustain_level",
      "mean": 0.8,
      "deviation": 0.15,
      "transform": "linear",
      "weight": 0.7,
      "provenance": {
       "source": "reasoned"
      }
     },
     {
      "feature": "envelope_attack_seconds",
      "mean": 0.05,
      "deviation": 2.718,
      "transform": "log",
      "weight": 0.6,
      "provenance": {
       "source": "reasoned"
      }
     },
     {
      "feature": "root_mean_square_level",
      "mean": 0.33,
      "deviation": 0.13,
      "transform": "linear",
      "weight": 0.7,
      "provenance": {
       "source": "reasoned"
      }
     },
     {
      "feature": "lufs",
      "mean": -10.0,
      "deviation": 5.0,
      "transform": "linear",
      "weight": 0.6,
      "provenance": {
       "source": "reasoned"
      }
     },
     {
      "feature": "length_seconds",
      "mean": 2.5,
      "deviation": 2.2,
      "transform": "log",
      "weight": 0.6,
      "provenance": {
       "source": "reasoned"
      }
     },
     {
      "feature": "mid_band_energy",
      "mean": 0.5,
      "deviation": 0.17,
      "transform": "linear",
      "weight": 0.5,
      "provenance": {
       "source": "reasoned"
      }
     },
     {
      "feature": "stationarity",
      "mean": 0.78,
      "deviation": 0.15,
      "transform": "linear",
      "weight": 0.5,
      "provenance": {
       "source": "reasoned"
      }
     }
    ],
    "discriminators": [
     "Loud, low, stable, harmonic — and HELD. A locomotive horn is a multi-chime air horn, so it sounds a fixed CHORD: harmonicity ~0.70 (gated >= 0.35), spectral_flatness ~0.16, a high partial_count, a flat pitch_slope_semitones_per_second, and a plateau envelope with a high sustain_ratio. Fully measurable.",
     "Against every other TRAINS subcategory: they are noise, rhythm or friction; this is the only stable TONE, and the harmonicity gate rejects the rolling stock outright.",
     "Against TRAINS-BRAKE (the other loud, pitched candidate): a squeal is INHARMONIC, UNSTABLE and in the kilohertz; a horn is harmonic, stable and a few hundred hertz. No overlap.",
     "Against ALARMS-SIREN: a siren sweeps its pitch; a horn does not. Against BOATS-HORN: an acoustic near-twin — text decides, though a ship's horn runs lower and longer.",
     "UCS sends steam whistles to WHISTLES-MECHANICAL, so a shrill single-tone whistle is NOT this.",
     "Doppler on a pass-by will bend the pitch; the pitch_slope deviation is set wide enough (2.0 st/s) to survive it."
    ],
    "confusable_with": [
     "BOATHorn",
     "TRNBrake",
     "TRNSteam",
     "TRNMisc"
    ]
   }
  },
  {
   "subcategory": "INTERIOR",
   "category_id": "TRNInt",
   "category_short": "TRN",
   "explanation": [
    "Interior trains",
    "from Diesel to Commuter",
    "onboard train sounds."
   ],
   "synonyms": [
    "Aboard",
    "Berth",
    "Cabin",
    "Caboose",
    "Car",
    "Carriage",
    "City",
    "Coach",
    "Commuter",
    "Compartment",
    "Dining",
    "Freight",
    "Inter-City",
    "Light",
    "Line",
    "Lounge",
    "Luggage",
    "Monorail",
    "Observation",
    "Onboard",
    "Overnight",
    "Passenger",
    "Racks",
    "Rail",
    "Railway",
    "Regional",
    "Rider",
    "Saloon",
    "Seating",
    "Sleeper",
    "Subway",
    "Train"
   ],
   "acoustic_signature": {
    "morphology": "sustained_noise",
    "separability": "signal_narrowable",
    "gates": [
     {
      "feature": "length_seconds",
      "min": 2.0,
      "max": 1800.0
     }
    ],
    "priors": [
     {
      "feature": "band_limit_high_hz",
      "mean": 6000.0,
      "deviation": 3000.0,
      "transform": "log",
      "weight": 0.8,
      "provenance": {
       "source": "reasoned"
      }
     },
     {
      "feature": "low_band_energy",
      "mean": 0.55,
      "deviation": 0.16,
      "transform": "linear",
      "weight": 0.9,
      "provenance": {
       "source": "reasoned"
      }
     },
     {
      "feature": "high_band_energy",
      "mean": 0.12,
      "deviation": 0.09,
      "transform": "linear",
      "weight": 0.6,
      "provenance": {
       "source": "reasoned"
      }
     },
     {
      "feature": "spectral_centroid_hz",
      "mean": 500.0,
      "deviation": 350.0,
      "transform": "log",
      "weight": 0.8,
      "provenance": {
       "source": "reasoned"
      }
     },
     {
      "feature": "spectral_slope_db_per_octave",
      "mean": -10.0,
      "deviation": 4.0,
      "transform": "linear",
      "weight": 0.6,
      "provenance": {
       "source": "reasoned"
      }
     },
     {
      "feature": "onset_periodicity",
      "mean": 0.45,
      "deviation": 0.22,
      "transform": "linear",
      "weight": 0.7,
      "provenance": {
       "source": "reasoned"
      }
     },
     {
      "feature": "onset_rate_per_second",
      "mean": 4.0,
      "deviation": 3.0,
      "transform": "log",
      "weight": 0.5,
      "provenance": {
       "source": "reasoned"
      }
     },
     {
      "feature": "stationarity",
      "mean": 0.72,
      "deviation": 0.16,
      "transform": "linear",
      "weight": 0.6,
      "provenance": {
       "source": "reasoned"
      }
     },
     {
      "feature": "spectral_flux",
      "mean": 0.09,
      "deviation": 0.05,
      "transform": "linear",
      "weight": 0.5,
      "provenance": {
       "source": "reasoned"
      }
     },
     {
      "feature": "length_seconds",
      "mean": 60.0,
      "deviation": 60.0,
      "transform": "log",
      "weight": 0.5,
      "provenance": {
       "source": "reasoned"
      }
     },
     {
      "feature": "crest_factor",
      "mean": 4.2,
      "deviation": 1.6,
      "transform": "log",
      "weight": 0.4,
      "provenance": {
       "source": "reasoned"
      }
     },
     {
      "feature": "root_mean_square_level",
      "mean": 0.11,
      "deviation": 0.07,
      "transform": "linear",
      "weight": 0.3,
      "provenance": {
       "source": "reasoned"
      }
     }
    ],
    "discriminators": [
     "An LP-filtered rumble bed like every vehicle interior — but with ONE feature the others do not have: the wheel clack comes up through the floor. A train interior is therefore the only INTERIOR in this set that carries a moderate onset_periodicity (~0.45) at a few events per second on top of a stationary LF bed. That is a genuine, if modest, discriminator against AIRCRAFT-INTERIOR (onset_periodicity ~0.12) and BOATS-INTERIOR (~0.18).",
     "Against TRAINS-CLACK (exterior or isolated): there the clack IS the signal — sharp, crest_factor ~7, HF present. Heard through the floor it is muffled and buried in the bed, so crest_factor stays low (~4.2) and band_limit_high_hz is capped.",
     "Diesel versus commuter interior is semantic."
    ],
    "confusable_with": [
     "AEROInt",
     "BOATInt",
     "TRNSbwy",
     "TRNClak",
     "TRNMisc"
    ]
   }
  },
  {
   "subcategory": "MECHANISM",
   "category_id": "TRNMech",
   "category_short": "TRN",
   "explanation": [
    "Coupling",
    "decoupling and other mechanical sounds relating to trains. Levers",
    "coal tender mechanics that are specific to a train."
   ],
   "synonyms": [
    "Axles",
    "Bearings",
    "Brakes",
    "Coupler",
    "Couplers",
    "Decouple",
    "Railway",
    "Shunt",
    "Shunter",
    "Suspension",
    "Switcher",
    "Wheels"
   ],
   "acoustic_signature": {
    "morphology": "impulsive_with_tail",
    "separability": "semantic_only",
    "gates": [
     {
      "feature": "length_seconds",
      "min": 0.05,
      "max": 120.0
     }
    ],
    "priors": [
     {
      "feature": "crest_factor",
      "mean": 9.0,
      "deviation": 3.5,
      "transform": "log",
      "weight": 0.7,
      "provenance": {
       "source": "reasoned"
      }
     },
     {
      "feature": "envelope_attack_seconds",
      "mean": 0.003,
      "deviation": 2.718,
      "transform": "log",
      "weight": 0.6,
      "provenance": {
       "source": "reasoned"
      }
     },
     {
      "feature": "root_mean_square_level",
      "mean": 0.22,
      "deviation": 0.12,
      "transform": "linear",
      "weight": 0.4,
      "provenance": {
       "source": "reasoned"
      }
     },
     {
      "feature": "decay_time_seconds_60db",
      "mean": 0.9,
      "deviation": 2.177,
      "transform": "log",
      "weight": 0.7,
      "provenance": {
       "source": "reasoned"
      }
     },
     {
      "feature": "inharmonicity",
      "mean": 0.65,
      "deviation": 0.2,
      "transform": "linear",
      "weight": 0.6,
      "provenance": {
       "source": "reasoned"
      }
     },
     {
      "feature": "low_band_energy",
      "mean": 0.35,
      "deviation": 0.17,
      "transform": "linear",
      "weight": 0.5,
      "provenance": {
       "source": "reasoned"
      }
     },
     {
      "feature": "envelope_temporal_centroid",
      "mean": 0.28,
      "deviation": 0.13,
      "transform": "linear",
      "weight": 0.5,
      "provenance": {
       "source": "reasoned"
      }
     },
     {
      "feature": "envelope_skewness",
      "mean": 2.2,
      "deviation": 1.3,
      "transform": "linear",
      "weight": 0.5,
      "provenance": {
       "source": "reasoned"
      }
     },
     {
      "feature": "transient_count",
      "mean": 3.0,
      "deviation": 3.0,
      "transform": "log",
      "weight": 0.5,
      "provenance": {
       "source": "reasoned"
      }
     },
     {
      "feature": "length_seconds",
      "mean": 3.0,
      "deviation": 3.0,
      "transform": "log",
      "weight": 0.4,
      "provenance": {
       "source": "reasoned"
      }
     },
     {
      "feature": "stationarity",
      "mean": 0.3,
      "deviation": 0.17,
      "transform": "linear",
      "weight": 0.5,
      "provenance": {
       "source": "reasoned"
      }
     }
    ],
    "discriminators": [
     "Couplings, shunting, axles. A coupler slam is a MASSIVE metal impact: very high crest_factor (~9), a millisecond attack, and a long inharmonic ring (decay_time_seconds_60db approaching a second) — the metal-impedance signature at full scale.",
     "But that is generic METAL-IMPACT morphology and nothing in it says 'train'. Semantic, and it will collide with BOATS-MECHANISM, AIRCRAFT-MECHANISM and the whole METAL category.",
     "Against TRAINS-CLACK: isolated impacts, not a sustained periodic train. CLACK gates at transient_count >= 4 with onset_periodicity >= 0.35; a couple of shunting bangs will not pass it."
    ],
    "confusable_with": [
     "TRNDoor",
     "TRNClak",
     "BOATMech",
     "AEROMech",
     "TRNBrake"
    ]
   }
  },
  {
   "subcategory": "MISC",
   "category_id": "TRNMisc",
   "category_short": "TRN",
   "explanation": [
    "Train sounds not fitting another category in this list."
   ],
   "synonyms": [
    "Miscellaneous",
    "Railway"
   ],
   "acoustic_signature": {
    "morphology": "complex",
    "separability": "semantic_only",
    "gates": [
     {
      "feature": "length_seconds",
      "min": 0.05,
      "max": 1800.0
     }
    ],
    "priors": [
     {
      "feature": "low_band_energy",
      "mean": 0.10438,
      "deviation": 0.2,
      "transform": "linear",
      "weight": 0.3,
      "provenance": {
       "source": "fsd50k_measured",
       "dataset": "FSD50K.dev",
       "clips": 297,
       "analyzer_version": "20260714.0350-d356b3ca938a00f9",
       "date": "2026-07",
       "measured_on": "all_unambiguous_clips",
       "reasoned_mean_before_calibration": 0.09285
      }
     },
     {
      "feature": "spectral_flatness",
      "mean": 0.10908,
      "deviation": 0.22,
      "transform": "linear",
      "weight": 0.3,
      "provenance": {
       "source": "fsd50k_measured",
       "dataset": "FSD50K.dev",
       "clips": 297,
       "analyzer_version": "20260714.0350-d356b3ca938a00f9",
       "date": "2026-07",
       "measured_on": "all_unambiguous_clips",
       "reasoned_mean_before_calibration": 0.12231
      }
     },
     {
      "feature": "length_seconds",
      "mean": 20.0,
      "deviation": 25.0,
      "transform": "log",
      "weight": 0.2,
      "provenance": {
       "source": "reasoned"
      }
     },
     {
      "feature": "harmonicity",
      "mean": 0.47409,
      "deviation": 0.4031,
      "transform": "linear",
      "weight": 0.2,
      "provenance": {
       "source": "fsd50k_measured",
       "dataset": "FSD50K.dev",
       "clips": 297,
       "analyzer_version": "20260714.0350-d356b3ca938a00f9",
       "date": "2026-07",
       "measured_on": "all_unambiguous_clips",
       "reasoned_mean_before_calibration": 0.43285
      }
     }
    ],
    "discriminators": [
     "The abstention target for TRAINS. Near-open gates and flat priors by design: it should win when the file is train-shaped but no sibling's morphology gate is met — level crossings, station announcements, yard ambience."
    ],
    "confusable_with": [
     "TRNDiesl",
     "TRNElec",
     "TRNSbwy",
     "TRNMech",
     "TRNClak"
    ],
    "measured_evidence": {
     "dataset": "FSD50K.dev — 40,966 human-labelled Freesound clips",
     "analyzer_version": "20260714.0350-d356b3ca938a00f9",
     "date": "2026-07",
     "clip_count": 297,
     "selection": "clips whose FSD50K labels map unambiguously to this one subcategory (high/medium crosswalk confidence only)",
     "contributing_fsd50k_classes": {
      "Train": 297
     },
     "feature_observations": {
      "complexity": {
       "clips": 296,
       "percentile_05": 1677.8,
       "median": 2812.2,
       "percentile_95": 4538.8
      },
      "crest_factor": {
       "clips": 28,
       "percentile_05": 3.6323,
       "median": 10.066,
       "percentile_95": 20.362,
       "measured_on": "one_shot_clips_only"
      },
      "envelope_attack_seconds": {
       "clips": 27,
       "percentile_05": 0.019955,
       "median": 0.37415,
       "percentile_95": 10.307,
       "measured_on": "one_shot_clips_only"
      },
      "envelope_decay_seconds": {
       "clips": 28,
       "percentile_05": 0.019955,
       "median": 0.68345,
       "percentile_95": 5.298,
       "measured_on": "one_shot_clips_only"
      },
      "envelope_kurtosis": {
       "clips": 28,
       "percentile_05": -1.2379,
       "median": 3.5355,
       "percentile_95": 61.674,
       "measured_on": "one_shot_clips_only"
      },
      "envelope_release_seconds": {
       "clips": 23,
       "percentile_05": 0.24943,
       "median": 2.1751,
       "percentile_95": 10.626,
       "measured_on": "one_shot_clips_only"
      },
      "envelope_skewness": {
       "clips": 28,
       "percentile_05": -0.12109,
       "median": 1.799,
       "percentile_95": 6.6269,
       "measured_on": "one_shot_clips_only"
      },
      "envelope_sustain_level": {
       "clips": 28,
       "percentile_05": 0.010399,
       "median": 0.072882,
       "percentile_95": 0.62087,
       "measured_on": "one_shot_clips_only"
      },
      "envelope_temporal_centroid": {
       "clips": 28,
       "percentile_05": 0.060648,
       "median": 0.3325,
       "percentile_95": 0.61085,
       "measured_on": "one_shot_clips_only"
      },
      "harmonicity": {
       "clips": 297,
       "percentile_05": 0.10403,
       "median": 0.47409,
       "percentile_95": 0.93077
      },
      "high_band_energy": {
       "clips": 297,
       "percentile_05": 0.10933,
       "median": 0.32429,
       "percentile_95": 0.71921
      },
      "inharmonicity": {
       "clips": 297,
       "percentile_05": 0.1239,
       "median": 0.42767,
       "percentile_95": 0.60288
      },
      "low_band_energy": {
       "clips": 297,
       "percentile_05": 0.010701,
       "median": 0.10438,
       "percentile_95": 0.41807
      },
      "mid_band_energy": {
       "clips": 297,
       "percentile_05": 0.20033,
       "median": 0.49833,
       "percentile_95": 0.71229
      },
      "onset_periodicity": {
       "clips": 297,
       "percentile_05": 0.10294,
       "median": 0.25789,
       "percentile_95": 0.54468
      },
      "onset_rate_per_second": {
       "clips": 297,
       "percentile_05": 0.088003,
       "median": 0.71213,
       "percentile_95": 2.6087
      },
      "partial_count": {
       "clips": 295,
       "percentile_05": 4.0,
       "median": 12.0,
       "percentile_95": 12.0
      },
      "pitch_hz": {
       "clips": 151,
       "percentile_05": 61.678,
       "median": 501.14,
       "percentile_95": 1633.3
      },
      "spectral_centroid_deviation_hz": {
       "clips": 297,
       "percentile_05": 162.89,
       "median": 503.28,
       "percentile_95": 1568.5
      },
      "spectral_centroid_hz": {
       "clips": 296,
       "percentile_05": 1037.6,
       "median": 2133.7,
       "percentile_95": 5259.7
      },
      "spectral_centroid_mean_hz": {
       "clips": 297,
       "percentile_05": 896.01,
       "median": 2116.8,
       "percentile_95": 4197.4
      },
      "spectral_centroid_slope_hz_per_second": {
       "clips": 297,
       "percentile_05": -165.71,
       "median": 4.5024,
       "percentile_95": 148.25
      },
      "spectral_entropy": {
       "clips": 297,
       "percentile_05": 0.27468,
       "median": 0.46739,
       "percentile_95": 0.6175
      },
      "spectral_flatness": {
       "clips": 297,
       "percentile_05": 0.033194,
       "median": 0.10908,
       "percentile_95": 0.32865
      },
      "spectral_flux": {
       "clips": 297,
       "percentile_05": 0.18869,
       "median": 0.21756,
       "percentile_95": 0.22667
      },
      "spectral_rolloff_hz": {
       "clips": 296,
       "percentile_05": 1473.9,
       "median": 4139.3,
       "percentile_95": 9831.3
      },
      "spectral_slope_db_per_octave": {
       "clips": 297,
       "percentile_05": -8.8893,
       "median": -5.4243,
       "percentile_95": -1.7853
      },
      "stationarity": {
       "clips": 297,
       "percentile_05": 0.0,
       "median": 0.37331,
       "percentile_95": 0.72527,
       "censored_at_floor_fraction": 0.249
      },
      "sustain_ratio": {
       "clips": 28,
       "percentile_05": 0.0061602,
       "median": 0.077778,
       "percentile_95": 0.86486,
       "measured_on": "one_shot_clips_only"
      },
      "syllabic_modulation_energy": {
       "clips": 296,
       "percentile_05": 0.064432,
       "median": 0.19325,
       "percentile_95": 0.45116
      },
      "transient_count": {
       "clips": 297,
       "percentile_05": 1.0,
       "median": 9.0,
       "percentile_95": 35.0
      },
      "zero_crossings_per_second": {
       "clips": 296,
       "percentile_05": 514.82,
       "median": 1904.1,
       "percentile_95": 5032.2
      }
     },
     "features_not_measurable_here": {
      "band_limit_high_hz": "left reasoned — see not_calibrated in fsd50k_calibration.json",
      "beats_per_minute": "left reasoned — see not_calibrated in fsd50k_calibration.json",
      "clipping_density": "left reasoned — see not_calibrated in fsd50k_calibration.json",
      "dc_offset": "left reasoned — see not_calibrated in fsd50k_calibration.json",
      "length_seconds": "left reasoned — see not_calibrated in fsd50k_calibration.json",
      "lufs": "left reasoned — see not_calibrated in fsd50k_calibration.json",
      "root_mean_square_level": "left reasoned — see not_calibrated in fsd50k_calibration.json",
      "sample_rate": "left reasoned — see not_calibrated in fsd50k_calibration.json",
      "stereo_width": "left reasoned — see not_calibrated in fsd50k_calibration.json",
      "total_harmonic_distortion": "left reasoned — see not_calibrated in fsd50k_calibration.json",
      "voicing_ratio": "left reasoned — see not_calibrated in fsd50k_calibration.json"
     },
     "caveat": "Amateur Freesound audio, mono, arbitrary normalization. Treat as a prior on the prior, not as truth. Duration, level, stereo width and band limit are NOT measurable here and are left reasoned."
    }
   }
  },
  {
   "subcategory": "STEAM",
   "category_id": "TRNSteam",
   "category_short": "TRN",
   "explanation": [
    "Old steam powered trains",
    "big smoke stack chugs."
   ],
   "synonyms": [
    "Boiler",
    "Chuffing",
    "Chugging",
    "Coal",
    "Firebox",
    "Heritage",
    "Hissing",
    "Locomotive",
    "Narrow-Gauge",
    "Piston",
    "Railway",
    "Smokestack",
    "Steam",
    "Steam-Powered",
    "Steaming",
    "Tender"
   ],
   "acoustic_signature": {
    "morphology": "complex",
    "separability": "signal_narrowable",
    "gates": [
     {
      "feature": "length_seconds",
      "min": 1.0,
      "max": 900.0
     }
    ],
    "priors": [
     {
      "feature": "onset_periodicity",
      "mean": 0.68,
      "deviation": 0.18,
      "transform": "linear",
      "weight": 0.9,
      "provenance": {
       "source": "reasoned"
      }
     },
     {
      "feature": "onset_rate_per_second",
      "mean": 2.5,
      "deviation": 2.0,
      "transform": "log",
      "weight": 0.9,
      "provenance": {
       "source": "reasoned"
      }
     },
     {
      "feature": "high_band_energy",
      "mean": 0.4,
      "deviation": 0.17,
      "transform": "linear",
      "weight": 0.8,
      "provenance": {
       "source": "reasoned"
      }
     },
     {
      "feature": "spectral_flatness",
      "mean": 0.58,
      "deviation": 0.16,
      "transform": "linear",
      "weight": 0.7,
      "provenance": {
       "source": "reasoned"
      }
     },
     {
      "feature": "zero_crossings_per_second",
      "mean": 5000.0,
      "deviation": 3000.0,
      "transform": "log",
      "weight": 0.6,
      "provenance": {
       "source": "reasoned"
      }
     },
     {
      "feature": "spectral_centroid_hz",
      "mean": 2400.0,
      "deviation": 1400.0,
      "transform": "log",
      "weight": 0.6,
      "provenance": {
       "source": "reasoned"
      }
     },
     {
      "feature": "low_band_energy",
      "mean": 0.28,
      "deviation": 0.15,
      "transform": "linear",
      "weight": 0.5,
      "provenance": {
       "source": "reasoned"
      }
     },
     {
      "feature": "harmonicity",
      "mean": 0.18,
      "deviation": 0.13,
      "transform": "linear",
      "weight": 0.6,
      "provenance": {
       "source": "reasoned"
      }
     },
     {
      "feature": "total_harmonic_distortion",
      "mean": 0.08,
      "deviation": 0.07,
      "transform": "linear",
      "weight": 0.5,
      "provenance": {
       "source": "reasoned"
      }
     },
     {
      "feature": "crest_factor",
      "mean": 5.5,
      "deviation": 2.2,
      "transform": "log",
      "weight": 0.6,
      "provenance": {
       "source": "reasoned"
      }
     },
     {
      "feature": "spectral_flux",
      "mean": 0.2,
      "deviation": 0.09,
      "transform": "linear",
      "weight": 0.5,
      "provenance": {
       "source": "reasoned"
      }
     },
     {
      "feature": "envelope_attack_seconds",
      "mean": 0.03,
      "deviation": 2.718,
      "transform": "log",
      "weight": 0.4,
      "provenance": {
       "source": "reasoned"
      }
     },
     {
      "feature": "length_seconds",
      "mean": 35.0,
      "deviation": 30.0,
      "transform": "log",
      "weight": 0.3,
      "provenance": {
       "source": "reasoned"
      }
     },
     {
      "feature": "stationarity",
      "mean": 0.48,
      "deviation": 0.2,
      "transform": "linear",
      "weight": 0.5,
      "provenance": {
       "source": "reasoned"
      }
     }
    ],
    "discriminators": [
     "A steam locomotive is TWO signatures at once, and both are measurable. (1) HISS: a broadband HF noise bed — spectral_flatness ~0.58, high_band_energy ~0.40, high zero_crossings_per_second — the AIR-HISS timbre exactly. (2) CHUFF: a slow RHYTHMIC exhaust beat on top — onset_periodicity ~0.68 at only ~1-5 events per second, because there are four exhaust strokes per driver revolution and the drivers turn slowly. HISS + SLOW-PERIODIC is the fingerprint, and it belongs to nothing else in TRAINS.",
     "Against TRAINS-DIESEL: a diesel is LF, distorted and pulses at TENS of hertz; steam is HF-bright, undistorted and pulses at a FEW per second. Both the spectral tilt and the onset rate are inverted.",
     "Against TRAINS-CLACK: clacks are sharper (crest_factor ~7, millisecond attacks) and FASTER (~3-8/s), and carry no hiss bed. A chuff has a soft attack (~30 ms).",
     "Against BOATS-STEAM: the same physics and the same signature. Text decides.",
     "The chuff rate rises with speed; the periodicity persists, so the rate prior is given a wide deviation."
    ],
    "confusable_with": [
     "BOATStm",
     "TRNDiesl",
     "TRNClak",
     "TRNMisc",
     "TRNHorn"
    ]
   }
  },
  {
   "subcategory": "SUBWAY",
   "category_id": "TRNSbwy",
   "category_short": "TRN",
   "explanation": [
    "Subways",
    "overtly 'underground' sounding trains",
    "above group city trains probably best in TRAINS-ELECTRIC"
   ],
   "synonyms": [
    "City",
    "Commuter",
    "Electric",
    "Mass",
    "Metro",
    "MRT",
    "Railcar",
    "Railway",
    "Rapid",
    "Subway",
    "System",
    "Train",
    "Transit",
    "Tube",
    "Tubes",
    "Underground",
    "Urban"
   ],
   "acoustic_signature": {
    "morphology": "complex",
    "separability": "semantic_only",
    "gates": [
     {
      "feature": "length_seconds",
      "min": 1.0,
      "max": 1800.0
     }
    ],
    "priors": [
     {
      "feature": "low_band_energy",
      "mean": 0.12254,
      "deviation": 0.18,
      "transform": "linear",
      "weight": 0.4,
      "provenance": {
       "source": "fsd50k_measured",
       "dataset": "FSD50K.dev",
       "clips": 269,
       "analyzer_version": "20260714.0350-d356b3ca938a00f9",
       "date": "2026-07",
       "measured_on": "all_unambiguous_clips",
       "reasoned_mean_before_calibration": 0.12448
      }
     },
     {
      "feature": "decay_time_seconds_60db",
      "mean": 1.8,
      "deviation": 1.2,
      "transform": "log",
      "weight": 0.5,
      "provenance": {
       "source": "reasoned"
      }
     },
     {
      "feature": "harmonicity",
      "mean": 0.5183,
      "deviation": 0.3419,
      "transform": "linear",
      "weight": 0.3,
      "provenance": {
       "source": "fsd50k_measured",
       "dataset": "FSD50K.dev",
       "clips": 269,
       "analyzer_version": "20260714.0350-d356b3ca938a00f9",
       "date": "2026-07",
       "measured_on": "all_unambiguous_clips",
       "reasoned_mean_before_calibration": 0.53844
      }
     },
     {
      "feature": "onset_periodicity",
      "mean": 0.20728,
      "deviation": 0.22,
      "transform": "linear",
      "weight": 0.3,
      "provenance": {
       "source": "fsd50k_measured",
       "dataset": "FSD50K.dev",
       "clips": 269,
       "analyzer_version": "20260714.0350-d356b3ca938a00f9",
       "date": "2026-07",
       "measured_on": "all_unambiguous_clips",
       "reasoned_mean_before_calibration": 0.45
      }
     },
     {
      "feature": "spectral_centroid_hz",
      "mean": 2139.5,
      "deviation": 700.0,
      "transform": "log",
      "weight": 0.3,
      "provenance": {
       "source": "fsd50k_measured",
       "dataset": "FSD50K.dev",
       "clips": 269,
       "analyzer_version": "20260714.0350-d356b3ca938a00f9",
       "date": "2026-07",
       "measured_on": "all_unambiguous_clips",
       "reasoned_mean_before_calibration": 2208.15382
      }
     },
     {
      "feature": "root_mean_square_level",
      "mean": 0.24,
      "deviation": 0.12,
      "transform": "linear",
      "weight": 0.3,
      "provenance": {
       "source": "reasoned"
      }
     },
     {
      "feature": "spectral_flux",
      "mean": 0.21951,
      "deviation": 0.08,
      "transform": "linear",
      "weight": 0.3,
      "provenance": {
       "source": "fsd50k_measured",
       "dataset": "FSD50K.dev",
       "clips": 269,
       "analyzer_version": "20260714.0350-d356b3ca938a00f9",
       "date": "2026-07",
       "measured_on": "all_unambiguous_clips",
       "reasoned_mean_before_calibration": 0.22028
      }
     },
     {
      "feature": "stationarity",
      "mean": 0.45923,
      "deviation": 0.2985,
      "transform": "linear",
      "weight": 0.3,
      "provenance": {
       "source": "fsd50k_measured",
       "dataset": "FSD50K.dev",
       "clips": 269,
       "analyzer_version": "20260714.0350-d356b3ca938a00f9",
       "date": "2026-07",
       "measured_on": "all_unambiguous_clips",
       "reasoned_mean_before_calibration": 0.47851
      }
     },
     {
      "feature": "length_seconds",
      "mean": 40.0,
      "deviation": 40.0,
      "transform": "log",
      "weight": 0.3,
      "provenance": {
       "source": "reasoned"
      }
     }
    ],
    "discriminators": [
     "UCS defines this by ENVIRONMENT, not by source: 'overtly underground sounding trains; above ground city trains probably best in TRAINS-ELECTRIC.' The vehicle is identical to TRAINS-ELECTRIC. What differs is the TUNNEL.",
     "So the only real handle is REVERBERATION — a long decay_time_seconds_60db (~1.8 s) and the heavy LF buildup of a confined concrete tube. That is an environment tell, not a source signature, which is why this is semantic_only rather than narrowable: a reverberant elevated station will fake it.",
     "The whole electric-traction stack sits underneath (whine, clack, brake squeal), so no single morphology dominates — hence 'complex'."
    ],
    "confusable_with": [
     "TRNElec",
     "TRNInt",
     "TRNClak",
     "TRNBrake",
     "TRNHspd"
    ],
    "measured_evidence": {
     "dataset": "FSD50K.dev — 40,966 human-labelled Freesound clips",
     "analyzer_version": "20260714.0350-d356b3ca938a00f9",
     "date": "2026-07",
     "clip_count": 269,
     "selection": "clips whose FSD50K labels map unambiguously to this one subcategory (high/medium crosswalk confidence only)",
     "contributing_fsd50k_classes": {
      "Subway_and_metro_and_underground": 269
     },
     "feature_observations": {
      "complexity": {
       "clips": 269,
       "percentile_05": 1577.3,
       "median": 2940.0,
       "percentile_95": 4328.0
      },
      "harmonicity": {
       "clips": 269,
       "percentile_05": 0.18509,
       "median": 0.5183,
       "percentile_95": 0.88416
      },
      "high_band_energy": {
       "clips": 269,
       "percentile_05": 0.11426,
       "median": 0.32459,
       "percentile_95": 0.59981
      },
      "inharmonicity": {
       "clips": 269,
       "percentile_05": 0.11188,
       "median": 0.41414,
       "percentile_95": 0.62932
      },
      "low_band_energy": {
       "clips": 269,
       "percentile_05": 0.029285,
       "median": 0.12254,
       "percentile_95": 0.36904
      },
      "mid_band_energy": {
       "clips": 269,
       "percentile_05": 0.29747,
       "median": 0.49611,
       "percentile_95": 0.75828
      },
      "onset_periodicity": {
       "clips": 269,
       "percentile_05": 0.09599,
       "median": 0.20728,
       "percentile_95": 0.37214
      },
      "onset_rate_per_second": {
       "clips": 269,
       "percentile_05": 0.26379,
       "median": 1.28,
       "percentile_95": 2.7942
      },
      "partial_count": {
       "clips": 268,
       "percentile_05": 6.0,
       "median": 12.0,
       "percentile_95": 12.0
      },
      "pitch_hz": {
       "clips": 106,
       "percentile_05": 81.215,
       "median": 334.09,
       "percentile_95": 1575.0
      },
      "spectral_centroid_deviation_hz": {
       "clips": 269,
       "percentile_05": 180.12,
       "median": 637.95,
       "percentile_95": 1587.7
      },
      "spectral_centroid_hz": {
       "clips": 269,
       "percentile_05": 990.35,
       "median": 2139.5,
       "percentile_95": 4011.1
      },
      "spectral_centroid_mean_hz": {
       "clips": 269,
       "percentile_05": 981.8,
       "median": 1719.1,
       "percentile_95": 3173.3
      },
      "spectral_centroid_slope_hz_per_second": {
       "clips": 269,
       "percentile_05": -225.85,
       "median": -11.603,
       "percentile_95": 158.55
      },
      "spectral_entropy": {
       "clips": 269,
       "percentile_05": 0.3214,
       "median": 0.42318,
       "percentile_95": 0.53981
      },
      "spectral_flatness": {
       "clips": 269,
       "percentile_05": 0.031858,
       "median": 0.11096,
       "percentile_95": 0.28125
      },
      "spectral_flux": {
       "clips": 269,
       "percentile_05": 0.19755,
       "median": 0.21951,
       "percentile_95": 0.2268
      },
      "spectral_rolloff_hz": {
       "clips": 269,
       "percentile_05": 1529.5,
       "median": 4060.7,
       "percentile_95": 9185.9
      },
      "spectral_slope_db_per_octave": {
       "clips": 269,
       "percentile_05": -8.6927,
       "median": -6.0545,
       "percentile_95": -3.1365
      },
      "stationarity": {
       "clips": 269,
       "percentile_05": 0.0,
       "median": 0.45923,
       "percentile_95": 0.75148
      },
      "syllabic_modulation_energy": {
       "clips": 268,
       "percentile_05": 0.11738,
       "median": 0.25589,
       "percentile_95": 0.43093
      },
      "transient_count": {
       "clips": 269,
       "percentile_05": 2.0,
       "median": 12.0,
       "percentile_95": 35.0
      },
      "zero_crossings_per_second": {
       "clips": 269,
       "percentile_05": 578.22,
       "median": 1661.8,
       "percentile_95": 3725.8
      }
     },
     "features_not_measurable_here": {
      "band_limit_high_hz": "left reasoned — see not_calibrated in fsd50k_calibration.json",
      "beats_per_minute": "left reasoned — see not_calibrated in fsd50k_calibration.json",
      "clipping_density": "left reasoned — see not_calibrated in fsd50k_calibration.json",
      "dc_offset": "left reasoned — see not_calibrated in fsd50k_calibration.json",
      "length_seconds": "left reasoned — see not_calibrated in fsd50k_calibration.json",
      "lufs": "left reasoned — see not_calibrated in fsd50k_calibration.json",
      "root_mean_square_level": "left reasoned — see not_calibrated in fsd50k_calibration.json",
      "sample_rate": "left reasoned — see not_calibrated in fsd50k_calibration.json",
      "stereo_width": "left reasoned — see not_calibrated in fsd50k_calibration.json",
      "total_harmonic_distortion": "left reasoned — see not_calibrated in fsd50k_calibration.json",
      "voicing_ratio": "left reasoned — see not_calibrated in fsd50k_calibration.json"
     },
     "caveat": "Amateur Freesound audio, mono, arbitrary normalization. Treat as a prior on the prior, not as truth. Duration, level, stereo width and band limit are NOT measurable here and are left reasoned."
    }
   }
  },
  {
   "subcategory": "TRAM",
   "category_id": "TRNTram",
   "category_short": "TRN",
   "explanation": [
    "Trolleys",
    "cable cars trams and streetcars. A Tram is 'pulled' along a cable",
    "so not self-powered. An electric tram would go to TRAINS-ELECTRIC."
   ],
   "synonyms": [
    "Cable",
    "Car",
    "Funicular",
    "Grip",
    "Light",
    "Mover",
    "People",
    "Rail",
    "Railway",
    "Streetcar",
    "Tram",
    "Tramcar",
    "Tramway",
    "Trolley",
    "Trolleybus"
   ],
   "acoustic_signature": {
    "morphology": "complex",
    "separability": "semantic_only",
    "gates": [
     {
      "feature": "length_seconds",
      "min": 1.0,
      "max": 900.0
     }
    ],
    "priors": [
     {
      "feature": "onset_periodicity",
      "mean": 0.35,
      "deviation": 0.22,
      "transform": "linear",
      "weight": 0.4,
      "provenance": {
       "source": "reasoned"
      }
     },
     {
      "feature": "harmonicity",
      "mean": 0.3,
      "deviation": 0.2,
      "transform": "linear",
      "weight": 0.3,
      "provenance": {
       "source": "reasoned"
      }
     },
     {
      "feature": "total_harmonic_distortion",
      "mean": 0.06,
      "deviation": 0.06,
      "transform": "linear",
      "weight": 0.4,
      "provenance": {
       "source": "reasoned"
      }
     },
     {
      "feature": "low_band_energy",
      "mean": 0.35,
      "deviation": 0.17,
      "transform": "linear",
      "weight": 0.3,
      "provenance": {
       "source": "reasoned"
      }
     },
     {
      "feature": "spectral_centroid_hz",
      "mean": 1400.0,
      "deviation": 900.0,
      "transform": "log",
      "weight": 0.3,
      "provenance": {
       "source": "reasoned"
      }
     },
     {
      "feature": "root_mean_square_level",
      "mean": 0.14,
      "deviation": 0.09,
      "transform": "linear",
      "weight": 0.3,
      "provenance": {
       "source": "reasoned"
      }
     },
     {
      "feature": "stationarity",
      "mean": 0.55,
      "deviation": 0.2,
      "transform": "linear",
      "weight": 0.3,
      "provenance": {
       "source": "reasoned"
      }
     },
     {
      "feature": "length_seconds",
      "mean": 30.0,
      "deviation": 30.0,
      "transform": "log",
      "weight": 0.3,
      "provenance": {
       "source": "reasoned"
      }
     }
    ],
    "discriminators": [
     "UCS draws a MECHANICAL line here, not an acoustic one: 'A Tram is pulled along a cable, so not self-powered. An electric tram would go to TRAINS-ELECTRIC.' Cable haulage is invisible to DSP.",
     "The one physical consequence worth recording is a NEGATIVE: a cable car has no prime mover aboard, so there is no engine pulse train and no traction whine — total_harmonic_distortion stays low and onset_periodicity is modest. What is left is rail rumble, wheel squeal on tight curves, gripper clanks and a bell: a scene, not a morphology, hence 'complex'.",
     "Against TRAINS-ELECTRIC: if a gliding traction whine is present (harmonicity high, pitch sliding), UCS's own rule sends it to TRAINS-ELECTRIC, not here."
    ],
    "confusable_with": [
     "TRNElec",
     "TRNSbwy",
     "TRNMisc",
     "TRNBrake"
    ]
   }
  }
 ]
}